{
   "appname": "docker-overseerr-nightly",
   "apppic": "./images/docker-overseerr-nightly.png",
   "appfolder": "./nightly/docker-overseerr-nightly",
   "newversion": "1054b4e2d7262d841fa83cde624f1138ad7bd23a",
   "appbranch": "develop",
   "baseimage": "ghcr.io/dockserver/docker-alpine:latest",
   "description": "Request management and media discovery tool for the Plex ecosystem",
   "body": "Upgrading docker-overseerr-nightly to 1054b4e2d7262d841fa83cde624f1138ad7bd23a",
   "user": "github-actions[bot]"
}
