{
   "appname": "docker-overseerr-nightly",
   "apppic": "./images/docker-overseerr-nightly.png",
   "appfolder": "./nightly/docker-overseerr-nightly",
   "newversion": "6428b8d4195c736a384441a761a746a35a3ad009",
   "appbranch": "develop",
   "baseimage": "ghcr.io/dockserver/docker-alpine:latest",
   "description": "Request management and media discovery tool for the Plex ecosystem",
   "body": "Upgrading docker-overseerr-nightly to 6428b8d4195c736a384441a761a746a35a3ad009",
   "user": "github-actions[bot]"
}
